{
    "Master":[
     {
      "Year": 2023,
      "Category": "Game of the Year",
      "Game": "Alan Wake 2",
      "Studio": "Remedy Entertainment\/Epic Games Publishing",
      "Winner": 0
     },
     {
      "Year": 2023,
      "Category": "Game of the Year",
      "Game": "Baldur’s Gate 3",
      "Studio": "Larian Studios",
      "Winner": 1
     },
     {
      "Year": 2023,
      "Category": "Game of the Year",
      "Game": "Marvel’s Spider-Man 2",
      "Studio": "Insomniac Games\/SIE",
      "Winner": 0
     },
     {
      "Year": 2023,
      "Category": "Game of the Year",
      "Game": "Resident Evil 4",
      "Studio": "Capcom",
      "Winner": 0
     },
     {
      "Year": 2023,
      "Category": "Game of the Year",
      "Game": "Super Mario Bros. Wonder",
      "Studio": "Nintendo",
      "Winner": 0
     },
     {
      "Year": 2023,
      "Category": "Game of the Year",
      "Game": "The Legend of Zelda: Tears of the Kingdom",
      "Studio": "Nintendo",
      "Winner": 0
     },
     {
      "Year": 2023,
      "Category": "Best Game Direction",
      "Game": "Alan Wake 2",
      "Studio": "Remedy Entertainment\/Epic Games Publishing",
      "Winner": 1
     },
     {
      "Year": 2023,
      "Category": "Best Game Direction",
      "Game": "Baldur’s Gate 3",
      "Studio": "Larian Studios",
      "Winner": 0
     },
     {
      "Year": 2023,
      "Category": "Best Game Direction",
      "Game": "Marvel’s Spider-Man 2",
      "Studio": "Insomniac Games\/SIE",
      "Winner": 0
     },
     {
      "Year": 2023,
      "Category": "Best Game Direction",
      "Game": "Super Mario Bros. Wonder",
      "Studio": "Nintendo",
      "Winner": 0
     },
     {
      "Year": 2023,
      "Category": "Best Game Direction",
      "Game": "The Legend of Zelda: Tears of the Kingdom",
      "Studio": "Nintendo",
      "Winner": 0
     },
     {
      "Year": 2023,
      "Category": "Best Adaption",
      "Game": "Castlevania: Nocturne",
      "Studio": "Powerhouse Animation\/Netflix",
      "Winner": 0
     },
     {
      "Year": 2023,
      "Category": "Best Adaption",
      "Game": "Gran Turismo",
      "Studio": "PlayStation Productions\/Sony Pictures",
      "Winner": 0
     },
     {
      "Year": 2023,
      "Category": "Best Adaption",
      "Game": "The Last of Us",
      "Studio": "PlayStation Productions\/HBO",
      "Winner": 1
     },
     {
      "Year": 2023,
      "Category": "Best Adaption",
      "Game": "The Super Mario Bros. Movie",
      "Studio": "Illumination\/Nintendo\/Universal Pictures",
      "Winner": 0
     },
     {
      "Year": 2023,
      "Category": "Best Adaption",
      "Game": "Twisted Metal",
      "Studio": "PlayStation Productions\/Peacock",
      "Winner": 0
     },
     {
      "Year": 2023,
      "Category": "Best Narrative",
      "Game": "Alan Wake 2",
      "Studio": "Remedy Entertainment\/Epic Games Publishing",
      "Winner": 1
     },
     {
      "Year": 2023,
      "Category": "Best Narrative",
      "Game": "Baldur’s Gate 3",
      "Studio": "Larian Studios",
      "Winner": 0
     },
     {
      "Year": 2023,
      "Category": "Best Narrative",
      "Game": "Cyberpunk 2077: Phantom Liberty",
      "Studio": "CD Projekt Red",
      "Winner": 0
     },
     {
      "Year": 2023,
      "Category": "Best Narrative",
      "Game": "Final Fantasy XVI",
      "Studio": "Square Enix",
      "Winner": 0
     },
     {
      "Year": 2023,
      "Category": "Best Narrative",
      "Game": "Marvel’s Spider-Man 2",
      "Studio": "Insomniac Games\/SIE",
      "Winner": 0
     },
     {
      "Year": 2023,
      "Category": "Best Art Direction",
      "Game": "Alan Wake 2",
      "Studio": "Remedy Entertainment\/Epic Games Publishing",
      "Winner": 1
     },
     {
      "Year": 2023,
      "Category": "Best Art Direction",
      "Game": "Hi-Fi Rush",
      "Studio": "Tango Gameworks\/Bethesda Softworks",
      "Winner": 0
     },
     {
      "Year": 2023,
      "Category": "Best Art Direction",
      "Game": "Lies of P",
      "Studio": "Round8 Studio\/Neowiz Games",
      "Winner": 0
     },
     {
      "Year": 2023,
      "Category": "Best Art Direction",
      "Game": "Super Mario Bros. Wonder",
      "Studio": "Nintendo",
      "Winner": 0
     },
     {
      "Year": 2023,
      "Category": "Best Art Direction",
      "Game": "The Legend of Zelda: Tears of the Kingdom",
      "Studio": "Nintendo",
      "Winner": 0
     },
     {
      "Year": 2023,
      "Category": "Best Score and Music",
      "Game": "Alan Wake 2, Composer Petri Alanko",
      "Studio": "Remedy Entertainment\/Epic Games Publishing",
      "Winner": 0
     },
     {
      "Year": 2023,
      "Category": "Best Score and Music",
      "Game": "Baldur’s Gate 3, Composer Borislav Slavov",
      "Studio": "Larian Studios",
      "Winner": 0
     },
     {
      "Year": 2023,
      "Category": "Best Score and Music",
      "Game": "Final Fantasy XVI, Composer Masayoshi Soken",
      "Studio": "Square Enix",
      "Winner": 1
     },
     {
      "Year": 2023,
      "Category": "Best Score and Music",
      "Game": "Hi-Fi Rush, Audio Director Shuichi Kobori",
      "Studio": "Tango Gameworks\/Bethesda Softworks",
      "Winner": 0
     },
     {
      "Year": 2023,
      "Category": "Best Score and Music",
      "Game": "The Legend of Zelda: Tears of the Kingdom, Composed by Nintendo Sound Team",
      "Studio": "Nintendo",
      "Winner": 0
     },
     {
      "Year": 2023,
      "Category": "Best Audio Design",
      "Game": "Alan Wake 2",
      "Studio": "Remedy Entertainment\/Epic Games Publishing",
      "Winner": 0
     },
     {
      "Year": 2023,
      "Category": "Best Audio Design",
      "Game": "Dead Space",
      "Studio": "Motive Studio\/EA",
      "Winner": 0
     },
     {
      "Year": 2023,
      "Category": "Best Audio Design",
      "Game": "Hi-Fi Rush",
      "Studio": "Tango Gameworks\/Bethesda Softworks",
      "Winner": 1
     },
     {
      "Year": 2023,
      "Category": "Best Audio Design",
      "Game": "Marvel’s Spider-Man 2",
      "Studio": "Insomniac Games\/SIE",
      "Winner": 0
     },
     {
      "Year": 2023,
      "Category": "Best Audio Design",
      "Game": "Resident Evil 4",
      "Studio": "Capcom",
      "Winner": 0
     },
     {
      "Year": 2023,
      "Category": "Innovation in Accessibility",
      "Game": "Diablo IV",
      "Studio": "Blizzard Entertainment",
      "Winner": 0
     },
     {
      "Year": 2023,
      "Category": "Innovation in Accessibility",
      "Game": "Forza Motorsport",
      "Studio": "Turn 10 Studios\/Xbox Game Studios",
      "Winner": 1
     },
     {
      "Year": 2023,
      "Category": "Innovation in Accessibility",
      "Game": "Hi-Fi Rush",
      "Studio": "Tango Gameworks\/Bethesda Softworks",
      "Winner": 0
     },
     {
      "Year": 2023,
      "Category": "Innovation in Accessibility",
      "Game": "Marvel’s Spider-Man 2",
      "Studio": "Insomniac Games\/SIE",
      "Winner": 0
     },
     {
      "Year": 2023,
      "Category": "Innovation in Accessibility",
      "Game": "Mortal Kombat 1",
      "Studio": "NetherRealm Studios\/WB Games",
      "Winner": 0
     },
     {
      "Year": 2023,
      "Category": "Innovation in Accessibility",
      "Game": "Street Fighter 6",
      "Studio": "Capcom",
      "Winner": 0
     },
     {
      "Year": 2023,
      "Category": "Games for Impact",
      "Game": "A Space for the Unbound",
      "Studio": "Mojiken Studio\/Toge Productions\/Chorus",
      "Winner": 0
     },
     {
      "Year": 2023,
      "Category": "Games for Impact",
      "Game": "Chants of Sennaar",
      "Studio": "Rundisc\/Focus Entertainment",
      "Winner": 0
     },
     {
      "Year": 2023,
      "Category": "Games for Impact",
      "Game": "Goodbye Volcano High",
      "Studio": "KO_OP",
      "Winner": 0
     },
     {
      "Year": 2023,
      "Category": "Games for Impact",
      "Game": "Tchia",
      "Studio": "Awaceb\/Kepler Interactive",
      "Winner": 1
     },
     {
      "Year": 2023,
      "Category": "Games for Impact",
      "Game": "Terra Nil",
      "Studio": "Free Lives\/Devolver\/Netflix",
      "Winner": 0
     },
     {
      "Year": 2023,
      "Category": "Games for Impact",
      "Game": "Venba",
      "Studio": "Visai Games",
      "Winner": 0
     },
     {
      "Year": 2023,
      "Category": "Best Ongoing Game",
      "Game": "Apex Legends",
      "Studio": "Respawn Entertainment\/EA",
      "Winner": 0
     },
     {
      "Year": 2023,
      "Category": "Best Ongoing Game",
      "Game": "Cyberpunk 2077",
      "Studio": "CD Projekt Red",
      "Winner": 1
     },
     {
      "Year": 2023,
      "Category": "Best Ongoing Game",
      "Game": "Final Fantasy XIV",
      "Studio": "Square Enix",
      "Winner": 0
     },
     {
      "Year": 2023,
      "Category": "Best Ongoing Game",
      "Game": "Fortnite",
      "Studio": "Epic Games",
      "Winner": 0
     },
     {
      "Year": 2023,
      "Category": "Best Ongoing Game",
      "Game": "Genshin Impact",
      "Studio": "HoYoverse",
      "Winner": 0
     },
     {
      "Year": 2023,
      "Category": "Best Community Support",
      "Game": "Baldur’s Gate 3",
      "Studio": "Larian Studios",
      "Winner": 1
     },
     {
      "Year": 2023,
      "Category": "Best Community Support",
      "Game": "Cyberpunk 2077",
      "Studio": "CD Projekt Red",
      "Winner": 0
     },
     {
      "Year": 2023,
      "Category": "Best Community Support",
      "Game": "Destiny 2",
      "Studio": "Bungie",
      "Winner": 0
     },
     {
      "Year": 2023,
      "Category": "Best Community Support",
      "Game": "Final Fantasy XIV",
      "Studio": "Square Enix",
      "Winner": 0
     },
     {
      "Year": 2023,
      "Category": "Best Community Support",
      "Game": "No Man’s Sky",
      "Studio": "Hello Games",
      "Winner": 0
     },
     {
      "Year": 2023,
      "Category": "Best Independent Game",
      "Game": "Cocoon",
      "Studio": "Geometric Interactive\/Annapurna Interactive",
      "Winner": 0
     },
     {
      "Year": 2023,
      "Category": "Best Independent Game",
      "Game": "Dave the Diver",
      "Studio": "MINTROCKET",
      "Winner": 0
     },
     {
      "Year": 2023,
      "Category": "Best Independent Game",
      "Game": "Dredge",
      "Studio": "Black Salt Games\/Team 17",
      "Winner": 0
     },
     {
      "Year": 2023,
      "Category": "Best Independent Game",
      "Game": "Sea of Stars",
      "Studio": "Sabotage Studio",
      "Winner": 1
     },
     {
      "Year": 2023,
      "Category": "Best Independent Game",
      "Game": "Viewfinder",
      "Studio": "Sad Owl Studios\/Thunderful Publishing",
      "Winner": 0
     },
     {
      "Year": 2023,
      "Category": "Best Debut Indie Game",
      "Game": "Cocoon",
      "Studio": "Geometric Interactive\/Annapurna Interactive",
      "Winner": 1
     },
     {
      "Year": 2023,
      "Category": "Best Debut Indie Game",
      "Game": "Dredge",
      "Studio": "Black Salt Games\/Team 17",
      "Winner": 0
     },
     {
      "Year": 2023,
      "Category": "Best Debut Indie Game",
      "Game": "Pizza Tower",
      "Studio": "Tour de Pizza",
      "Winner": 0
     },
     {
      "Year": 2023,
      "Category": "Best Debut Indie Game",
      "Game": "Venba",
      "Studio": "Visai Games",
      "Winner": 0
     },
     {
      "Year": 2023,
      "Category": "Best Debut Indie Game",
      "Game": "Viewfinder",
      "Studio": "Sad Owl Studios\/Thunderful Publishing",
      "Winner": 0
     },
     {
      "Year": 2023,
      "Category": "Best Mobile Game",
      "Game": "Final Fantasy VII: Ever Crisis",
      "Studio": "Applibot\/Square Enix",
      "Winner": 0
     },
     {
      "Year": 2023,
      "Category": "Best Mobile Game",
      "Game": "Honkai: Star Rail",
      "Studio": "HoYoverse",
      "Winner": 1
     },
     {
      "Year": 2023,
      "Category": "Best Mobile Game",
      "Game": "Hello Kitty Island Adventure",
      "Studio": "Sunblink Entertainment",
      "Winner": 0
     },
     {
      "Year": 2023,
      "Category": "Best Mobile Game",
      "Game": "Monster Hunter Now",
      "Studio": "Niantic\/Capcom",
      "Winner": 0
     },
     {
      "Year": 2023,
      "Category": "Best Mobile Game",
      "Game": "Terra Nil",
      "Studio": "Free Lives\/Devolver\/Netflix",
      "Winner": 0
     },
     {
      "Year": 2023,
      "Category": "Best VR\/AR Game",
      "Game": "Gran Turismo 7",
      "Studio": "Polyphony Digital\/SIE",
      "Winner": 0
     },
     {
      "Year": 2023,
      "Category": "Best VR\/AR Game",
      "Game": "Humanity",
      "Studio": "tha LTD\/Enhance Games",
      "Winner": 0
     },
     {
      "Year": 2023,
      "Category": "Best VR\/AR Game",
      "Game": "Horizon Call of the Mountain",
      "Studio": "Guerrilla Games\/Firesprite\/SIE",
      "Winner": 0
     },
     {
      "Year": 2023,
      "Category": "Best VR\/AR Game",
      "Game": "Resident Evil Village VR Mode",
      "Studio": "Capcom",
      "Winner": 1
     },
     {
      "Year": 2023,
      "Category": "Best VR\/AR Game",
      "Game": "Synapse",
      "Studio": "nDreams",
      "Winner": 0
     },
     {
      "Year": 2023,
      "Category": "Best Action Game",
      "Game": "Armored Core VI: Fires of Rubicon",
      "Studio": "FromSoftware\/Bandai Namco",
      "Winner": 1
     },
     {
      "Year": 2023,
      "Category": "Best Action Game",
      "Game": "Dead Island 2",
      "Studio": "Dambuster Studios\/Deep Silver",
      "Winner": 0
     },
     {
      "Year": 2023,
      "Category": "Best Action Game",
      "Game": "Ghostrunner 2",
      "Studio": "One More Level\/505 Games",
      "Winner": 0
     },
     {
      "Year": 2023,
      "Category": "Best Action Game",
      "Game": "Hi-Fi Rush",
      "Studio": "Tango Gameworks\/Bethesda Softworks",
      "Winner": 0
     },
     {
      "Year": 2023,
      "Category": "Best Action Game",
      "Game": "Remnant 2",
      "Studio": "Gunfire Games\/Gearbox Publishing",
      "Winner": 0
     },
     {
      "Year": 2023,
      "Category": "Best Action\/Adventure Game",
      "Game": "Alan Wake 2",
      "Studio": "Remedy Entertainment\/Epic Games Publishing",
      "Winner": 0
     },
     {
      "Year": 2023,
      "Category": "Best Action\/Adventure Game",
      "Game": "Marvel’s Spider-Man 2",
      "Studio": "Insomniac Games\/SIE",
      "Winner": 0
     },
     {
      "Year": 2023,
      "Category": "Best Action\/Adventure Game",
      "Game": "Resident Evil 4",
      "Studio": "Capcom",
      "Winner": 0
     },
     {
      "Year": 2023,
      "Category": "Best Action\/Adventure Game",
      "Game": "Star Wars Jedi: Survivor",
      "Studio": "Respawn Entertainment\/EA",
      "Winner": 0
     },
     {
      "Year": 2023,
      "Category": "Best Action\/Adventure Game",
      "Game": "The Legend of Zelda: Tears of the Kingdom",
      "Studio": "Nintendo",
      "Winner": 1
     },
     {
      "Year": 2023,
      "Category": "Best RPG",
      "Game": "Baldur’s Gate 3",
      "Studio": "Larian Studios",
      "Winner": 1
     },
     {
      "Year": 2023,
      "Category": "Best RPG",
      "Game": "Final Fantasy XVI",
      "Studio": "Square Enix",
      "Winner": 0
     },
     {
      "Year": 2023,
      "Category": "Best RPG",
      "Game": "Lies of P",
      "Studio": "Round8 Studio\/Neowiz Games",
      "Winner": 0
     },
     {
      "Year": 2023,
      "Category": "Best RPG",
      "Game": "Sea of Stars",
      "Studio": "Sabotage Studio",
      "Winner": 0
     },
     {
      "Year": 2023,
      "Category": "Best RPG",
      "Game": "Starfield",
      "Studio": "Bethesda Game Studios\/Bethesda",
      "Winner": 0
     },
     {
      "Year": 2023,
      "Category": "Best Fighting Game",
      "Game": "God of Rock",
      "Studio": "Modus Studios Brazil\/Modus Games",
      "Winner": 0
     },
     {
      "Year": 2023,
      "Category": "Best Fighting Game",
      "Game": "Mortal Kombat 1",
      "Studio": "NetherRealm Studios\/WB Games",
      "Winner": 0
     },
     {
      "Year": 2023,
      "Category": "Best Fighting Game",
      "Game": "Nickelodeon All-Star Brawl 2",
      "Studio": "Ludosity\/Fair Play Labs\/GameMill",
      "Winner": 0
     },
     {
      "Year": 2023,
      "Category": "Best Fighting Game",
      "Game": "Pocket Bravery",
      "Studio": "Statera Studio\/PQube",
      "Winner": 0
     },
     {
      "Year": 2023,
      "Category": "Best Fighting Game",
      "Game": "Street Fighter 6",
      "Studio": "Capcom",
      "Winner": 1
     },
     {
      "Year": 2023,
      "Category": "Best Family Game",
      "Game": "Disney Illusion Island",
      "Studio": "Dlala Studios\/Disney",
      "Winner": 0
     },
     {
      "Year": 2023,
      "Category": "Best Family Game",
      "Game": "Party Animals",
      "Studio": "Recreate Games",
      "Winner": 0
     },
     {
      "Year": 2023,
      "Category": "Best Family Game",
      "Game": "Pikmin 4",
      "Studio": "Nintendo",
      "Winner": 0
     },
     {
      "Year": 2023,
      "Category": "Best Family Game",
      "Game": "Sonic Superstars",
      "Studio": "Arzest\/Sonic Team\/Sega",
      "Winner": 0
     },
     {
      "Year": 2023,
      "Category": "Best Family Game",
      "Game": "Super Mario Bros. Wonder",
      "Studio": "Nintendo",
      "Winner": 1
     },
     {
      "Year": 2023,
      "Category": "Best Sim\/Strategy Game",
      "Game": "Advance Wars 1+2: Re-Boot Camp",
      "Studio": "WayForward\/Nintendo",
      "Winner": 0
     },
     {
      "Year": 2023,
      "Category": "Best Sim\/Strategy Game",
      "Game": "Cities: Skylines II",
      "Studio": "Colossal Order\/Paradox Interactive",
      "Winner": 0
     },
     {
      "Year": 2023,
      "Category": "Best Sim\/Strategy Game",
      "Game": "Company of Heroes 3",
      "Studio": "Relic Entertainment\/Sega",
      "Winner": 0
     },
     {
      "Year": 2023,
      "Category": "Best Sim\/Strategy Game",
      "Game": "Fire Emblem Engage",
      "Studio": "Intelligent Systems\/Nintendo",
      "Winner": 0
     },
     {
      "Year": 2023,
      "Category": "Best Sim\/Strategy Game",
      "Game": "Pikmin 4",
      "Studio": "Nintendo",
      "Winner": 1
     },
     {
      "Year": 2023,
      "Category": "Best Sports\/Racing",
      "Game": "EA Sports FC 24",
      "Studio": "EA Vancouver\/EA Romania\/EA Sports",
      "Winner": 0
     },
     {
      "Year": 2023,
      "Category": "Best Sports\/Racing",
      "Game": "F1 23",
      "Studio": "Codemasters\/EA Sports",
      "Winner": 0
     },
     {
      "Year": 2023,
      "Category": "Best Sports\/Racing",
      "Game": "Forza Motorsport",
      "Studio": "Turn 10 Studios\/Xbox Game Studios",
      "Winner": 1
     },
     {
      "Year": 2023,
      "Category": "Best Sports\/Racing",
      "Game": "Hot Wheels Unleashed 2: Turbocharged",
      "Studio": "Milestone",
      "Winner": 0
     },
     {
      "Year": 2023,
      "Category": "Best Sports\/Racing",
      "Game": "The Crew Motorfest",
      "Studio": "Ubisoft Ivory Tower\/Ubisoft",
      "Winner": 0
     },
     {
      "Year": 2023,
      "Category": "Best Multiplayer Present by Discord",
      "Game": "Baldur’s Gate 3",
      "Studio": "Larian Studios",
      "Winner": 1
     },
     {
      "Year": 2023,
      "Category": "Best Multiplayer Present by Discord",
      "Game": "Diablo IV",
      "Studio": "Blizzard Entertainment",
      "Winner": 0
     },
     {
      "Year": 2023,
      "Category": "Best Multiplayer Present by Discord",
      "Game": "Party Animals",
      "Studio": "Recreate Games",
      "Winner": 0
     },
     {
      "Year": 2023,
      "Category": "Best Multiplayer Present by Discord",
      "Game": "Street Fighter 6",
      "Studio": "Capcom",
      "Winner": 0
     },
     {
      "Year": 2023,
      "Category": "Best Multiplayer Present by Discord",
      "Game": "Super Mario Bros. Wonder",
      "Studio": "Nintendo",
      "Winner": 0
     },
     {
      "Year": 2023,
      "Category": "Players' Voice",
      "Game": "Baldur’s Gate 3",
      "Studio": "Larian Studios",
      "Winner": 1
     },
     {
      "Year": 2023,
      "Category": "Players' Voice",
      "Game": "Cyberpunk 2077: Phantom Liberty",
      "Studio": "CD Projekt Red",
      "Winner": 0
     },
     {
      "Year": 2023,
      "Category": "Players' Voice",
      "Game": "Genshin Impact",
      "Studio": "HoYoverse",
      "Winner": 0
     },
     {
      "Year": 2023,
      "Category": "Players' Voice",
      "Game": "Marvel’s Spider-Man 2",
      "Studio": "Insomniac Games\/SIE",
      "Winner": 0
     },
     {
      "Year": 2023,
      "Category": "Players' Voice",
      "Game": "The Legend of Zelda: Tears of the Kingdom",
      "Studio": "Nintendo",
      "Winner": 0
     },
     {
      "Year": 2023,
      "Category": "Most Anticipated Game",
      "Game": "Final Fantasy VII Rebirth",
      "Studio": "Square Enix",
      "Winner": 1
     },
     {
      "Year": 2023,
      "Category": "Most Anticipated Game",
      "Game": "Hades II",
      "Studio": "Supergiant Games",
      "Winner": 0
     },
     {
      "Year": 2023,
      "Category": "Most Anticipated Game",
      "Game": "Like A Dragon: Infinite Wealth",
      "Studio": "Ryu Ga Gotoku Studio\/Sega",
      "Winner": 0
     },
     {
      "Year": 2023,
      "Category": "Most Anticipated Game",
      "Game": "Star Wars Outlaws",
      "Studio": "Massive Entertainment\/Ubisoft",
      "Winner": 0
     },
     {
      "Year": 2023,
      "Category": "Most Anticipated Game",
      "Game": "Tekken 8",
      "Studio": "Bandai Namco\/Arika",
      "Winner": 0
     },
     {
      "Year": 2023,
      "Category": "Best eSports Game",
      "Game": "Counter-Strike 2",
      "Studio": "Valve",
      "Winner": 0
     },
     {
      "Year": 2023,
      "Category": "Best eSports Game",
      "Game": "Dota 2",
      "Studio": "Valve",
      "Winner": 0
     },
     {
      "Year": 2023,
      "Category": "Best eSports Game",
      "Game": "League of Legends",
      "Studio": "Riot Games",
      "Winner": 0
     },
     {
      "Year": 2023,
      "Category": "Best eSports Game",
      "Game": "PUBG Mobile",
      "Studio": "LightSpeed Studios\/Tencent Games",
      "Winner": 0
     },
     {
      "Year": 2023,
      "Category": "Best eSports Game",
      "Game": "Valorant",
      "Studio": "Riot Games",
      "Winner": 1
     },
     {
      "Year": 2022,
      "Category": "Game of the Year",
      "Game": "A Plague Tale: Requiem",
      "Studio": "Asobo Studio\/Focus Entertainment",
      "Winner": 0
     },
     {
      "Year": 2022,
      "Category": "Game of the Year",
      "Game": "Elden Ring",
      "Studio": "FromSoftware\/Bandai Namco",
      "Winner": 1
     },
     {
      "Year": 2022,
      "Category": "Game of the Year",
      "Game": "God of War Ragnarök",
      "Studio": "Sony Santa Monica\/SIE",
      "Winner": 0
     },
     {
      "Year": 2022,
      "Category": "Game of the Year",
      "Game": "Horizon Forbidden West",
      "Studio": "Guerrilla Games\/SIE",
      "Winner": 0
     },
     {
      "Year": 2022,
      "Category": "Game of the Year",
      "Game": "Stray",
      "Studio": "BlueTwelve Studio\/Annapurna",
      "Winner": 0
     },
     {
      "Year": 2022,
      "Category": "Game of the Year",
      "Game": "Xenoblade Chronicles 3",
      "Studio": "Monolith Soft\/Nintendo",
      "Winner": 0
     },
     {
      "Year": 2022,
      "Category": "Best Game Direction",
      "Game": "Elden Ring",
      "Studio": "FromSoftware\/Bandai Namco",
      "Winner": 1
     },
     {
      "Year": 2022,
      "Category": "Best Game Direction",
      "Game": "God of War Ragnarök",
      "Studio": "Sony Santa Monica\/SIE",
      "Winner": 0
     },
     {
      "Year": 2022,
      "Category": "Best Game Direction",
      "Game": "Horizon Forbidden West",
      "Studio": "Guerrilla Games\/SIE",
      "Winner": 0
     },
     {
      "Year": 2022,
      "Category": "Best Game Direction",
      "Game": "Immortality",
      "Studio": "Half Mermaid",
      "Winner": 0
     },
     {
      "Year": 2022,
      "Category": "Best Game Direction",
      "Game": "Stray",
      "Studio": "BlueTwelve Studio\/Annapurna",
      "Winner": 0
     },
     {
      "Year": 2022,
      "Category": "Best Narrative",
      "Game": "A Plague Tale: Requiem",
      "Studio": "Asobo Studio\/Focus Entertainment",
      "Winner": 0
     },
     {
      "Year": 2022,
      "Category": "Best Narrative",
      "Game": "Elden Ring",
      "Studio": "FromSoftware\/Bandai Namco",
      "Winner": 0
     },
     {
      "Year": 2022,
      "Category": "Best Narrative",
      "Game": "God of War Ragnarök",
      "Studio": "Sony Santa Monica\/SIE",
      "Winner": 1
     },
     {
      "Year": 2022,
      "Category": "Best Narrative",
      "Game": "Horizon Forbidden West",
      "Studio": "Guerrilla Games\/SIE",
      "Winner": 0
     },
     {
      "Year": 2022,
      "Category": "Best Narrative",
      "Game": "Immortality",
      "Studio": "Half Mermaid",
      "Winner": 0
     },
     {
      "Year": 2022,
      "Category": "Best Art Direction",
      "Game": "Elden Ring",
      "Studio": "FromSoftware\/Bandai Namco",
      "Winner": 1
     },
     {
      "Year": 2022,
      "Category": "Best Art Direction",
      "Game": "God of War Ragnarök",
      "Studio": "Sony Santa Monica\/SIE",
      "Winner": 0
     },
     {
      "Year": 2022,
      "Category": "Best Art Direction",
      "Game": "Horizon Forbidden West",
      "Studio": "Guerrilla Games\/SIE",
      "Winner": 0
     },
     {
      "Year": 2022,
      "Category": "Best Art Direction",
      "Game": "Scorn",
      "Studio": "Ebb Software\/Kepler Interactive",
      "Winner": 0
     },
     {
      "Year": 2022,
      "Category": "Best Art Direction",
      "Game": "Stray",
      "Studio": "BlueTwelve Studio\/Annapurna",
      "Winner": 0
     },
     {
      "Year": 2022,
      "Category": "Best Score and Music",
      "Game": "A Plague Tale: Requiem",
      "Studio": "Olivier Deriviere",
      "Winner": 0
     },
     {
      "Year": 2022,
      "Category": "Best Score and Music",
      "Game": "Elden Ring",
      "Studio": "Tsukasa Saitoh",
      "Winner": 0
     },
     {
      "Year": 2022,
      "Category": "Best Score and Music",
      "Game": "God of War Ragnarök - WINNER",
      "Studio": "Bear McCreary",
      "Winner": 1
     },
     {
      "Year": 2022,
      "Category": "Best Score and Music",
      "Game": "Metal: Hellsinger",
      "Studio": "Two Feathers",
      "Winner": 0
     },
     {
      "Year": 2022,
      "Category": "Best Score and Music",
      "Game": "Xenoblade Chronicles 3",
      "Studio": "Yasunori Mitsuda",
      "Winner": 0
     },
     {
      "Year": 2022,
      "Category": "Best Audio Design",
      "Game": "Call of Duty: Modern Warfare II",
      "Studio": "Infinity Ward\/Activision",
      "Winner": 0
     },
     {
      "Year": 2022,
      "Category": "Best Audio Design",
      "Game": "Elden Ring",
      "Studio": "FromSoftware\/Bandai Namco",
      "Winner": 0
     },
     {
      "Year": 2022,
      "Category": "Best Audio Design",
      "Game": "God of War Ragnarök",
      "Studio": "Sony Santa Monica\/SIE",
      "Winner": 1
     },
     {
      "Year": 2022,
      "Category": "Best Audio Design",
      "Game": "Gran Turismo 7",
      "Studio": "Polyphony Digital\/SIE",
      "Winner": 0
     },
     {
      "Year": 2022,
      "Category": "Best Audio Design",
      "Game": "Horizon Forbidden West",
      "Studio": "Guerrilla Games\/SIE",
      "Winner": 0
     },
     {
      "Year": 2022,
      "Category": "Games for Impact",
      "Game": "A Memoir Blue",
      "Studio": "Cloisters Interactive\/Annapurna",
      "Winner": 0
     },
     {
      "Year": 2022,
      "Category": "Games for Impact",
      "Game": "As Dusk Falls",
      "Studio": "Interior Night\/Xbox Game Studios",
      "Winner": 1
     },
     {
      "Year": 2022,
      "Category": "Games for Impact",
      "Game": "Citizen Sleeper",
      "Studio": "Jump Over The Age\/Fellow Traveller",
      "Winner": 0
     },
     {
      "Year": 2022,
      "Category": "Games for Impact",
      "Game": "Endling - Extinction is Forever",
      "Studio": "Herobeat Studios\/HandyGames",
      "Winner": 0
     },
     {
      "Year": 2022,
      "Category": "Games for Impact",
      "Game": "Hindsight",
      "Studio": "Team Hindsight\/Annapurna",
      "Winner": 0
     },
     {
      "Year": 2022,
      "Category": "Games for Impact",
      "Game": "I Was a Teenage Exocolonist",
      "Studio": "Northway Games\/Finji",
      "Winner": 0
     },
     {
      "Year": 2022,
      "Category": "Best Ongoing Game",
      "Game": "Apex Legends",
      "Studio": "Respawn Entertainment\/EA",
      "Winner": 0
     },
     {
      "Year": 2022,
      "Category": "Best Ongoing Game",
      "Game": "Destiny 2",
      "Studio": "Bungie",
      "Winner": 0
     },
     {
      "Year": 2022,
      "Category": "Best Ongoing Game",
      "Game": "FINAL FANTASY XIV",
      "Studio": "Square Enix",
      "Winner": 1
     },
     {
      "Year": 2022,
      "Category": "Best Ongoing Game",
      "Game": "Fortnite",
      "Studio": "Epic Games",
      "Winner": 0
     },
     {
      "Year": 2022,
      "Category": "Best Ongoing Game",
      "Game": "Genshin Impact",
      "Studio": "HoYoverse",
      "Winner": 0
     },
     {
      "Year": 2022,
      "Category": "Best Independent Game",
      "Game": "Cult of the Lamb",
      "Studio": "Massive Monster \/ Devolver Digital",
      "Winner": 0
     },
     {
      "Year": 2022,
      "Category": "Best Independent Game",
      "Game": "Neon White",
      "Studio": "Angel Matrix\/Annapurna",
      "Winner": 0
     },
     {
      "Year": 2022,
      "Category": "Best Independent Game",
      "Game": "Sifu",
      "Studio": "Sloclap",
      "Winner": 0
     },
     {
      "Year": 2022,
      "Category": "Best Independent Game",
      "Game": "Stray",
      "Studio": "BlueTwelve Studio\/Annapurna",
      "Winner": 1
     },
     {
      "Year": 2022,
      "Category": "Best Independent Game",
      "Game": "TUNIC",
      "Studio": "TUNIC Team\/Finji",
      "Winner": 0
     },
     {
      "Year": 2022,
      "Category": "Best Debut Indie Game",
      "Game": "Neon White",
      "Studio": "Angel Matrix\/Annapurna",
      "Winner": 0
     },
     {
      "Year": 2022,
      "Category": "Best Debut Indie Game",
      "Game": "NORCO",
      "Studio": "Geography of Robots\/Raw Fury",
      "Winner": 0
     },
     {
      "Year": 2022,
      "Category": "Best Debut Indie Game",
      "Game": "Stray",
      "Studio": "BlueTwelve Studio\/Annapurna",
      "Winner": 1
     },
     {
      "Year": 2022,
      "Category": "Best Debut Indie Game",
      "Game": "TUNIC",
      "Studio": "TUNIC Team\/Finji",
      "Winner": 0
     },
     {
      "Year": 2022,
      "Category": "Best Debut Indie Game",
      "Game": "Vampire Survivors",
      "Studio": "poncle",
      "Winner": 0
     },
     {
      "Year": 2022,
      "Category": "Best Community Support",
      "Game": "Apex Legends",
      "Studio": "Respawn Entertainment\/EA",
      "Winner": 0
     },
     {
      "Year": 2022,
      "Category": "Best Community Support",
      "Game": "Destiny 2",
      "Studio": "Bungie",
      "Winner": 0
     },
     {
      "Year": 2022,
      "Category": "Best Community Support",
      "Game": "FINAL FANTASY XIV",
      "Studio": "Square Enix",
      "Winner": 1
     },
     {
      "Year": 2022,
      "Category": "Best Community Support",
      "Game": "Fortnite",
      "Studio": "Epic Games",
      "Winner": 0
     },
     {
      "Year": 2022,
      "Category": "Best Community Support",
      "Game": "No Man's Sky",
      "Studio": "Hello Games",
      "Winner": 0
     },
     {
      "Year": 2022,
      "Category": "Best Mobile Game",
      "Game": "Apex Legends Mobile",
      "Studio": "Lightspeed & Quantum\/Respawn Entertainment\/EA",
      "Winner": 0
     },
     {
      "Year": 2022,
      "Category": "Best Mobile Game",
      "Game": "Diablo Immortal",
      "Studio": "Blizzard\/NetEase",
      "Winner": 0
     },
     {
      "Year": 2022,
      "Category": "Best Mobile Game",
      "Game": "Genshin Impact",
      "Studio": "HoYoverse",
      "Winner": 0
     },
     {
      "Year": 2022,
      "Category": "Best Mobile Game",
      "Game": "MARVEL SNAP",
      "Studio": "Second Dinner Studios\/Nuverse",
      "Winner": 1
     },
     {
      "Year": 2022,
      "Category": "Best Mobile Game",
      "Game": "Tower of Fantasy",
      "Studio": "Hotta Studio\/Perfect World\/Level Infinite",
      "Winner": 0
     },
     {
      "Year": 2022,
      "Category": "Best VR\/AR Game",
      "Game": "After the Fall",
      "Studio": "Vertigo Games",
      "Winner": 0
     },
     {
      "Year": 2022,
      "Category": "Best VR\/AR Game",
      "Game": "Among Us VR",
      "Studio": "Schell Games\/InnerSloth",
      "Winner": 0
     },
     {
      "Year": 2022,
      "Category": "Best VR\/AR Game",
      "Game": "BONELAB",
      "Studio": "Stress Level Zero",
      "Winner": 0
     },
     {
      "Year": 2022,
      "Category": "Best VR\/AR Game",
      "Game": "Moss: Book II",
      "Studio": "Polyarc",
      "Winner": 1
     },
     {
      "Year": 2022,
      "Category": "Best VR\/AR Game",
      "Game": "Red Matter 2",
      "Studio": "Vertical Robot",
      "Winner": 0
     },
     {
      "Year": 2022,
      "Category": "Best Action",
      "Game": "Bayonetta 3",
      "Studio": "Platinum Games\/Nintendo",
      "Winner": 1
     },
     {
      "Year": 2022,
      "Category": "Best Action",
      "Game": "Call of Duty: Modern Warfare II",
      "Studio": "Infinity Ward\/Activision",
      "Winner": 0
     },
     {
      "Year": 2022,
      "Category": "Best Action",
      "Game": "Neon White",
      "Studio": "Angel Matrix\/Annapurna",
      "Winner": 0
     },
     {
      "Year": 2022,
      "Category": "Best Action",
      "Game": "Sifu",
      "Studio": "Sloclap",
      "Winner": 0
     },
     {
      "Year": 2022,
      "Category": "Best Action",
      "Game": "Teenage Mutant Ninja Turtles: Shredder's Revenge",
      "Studio": "Tribute Games\/Dotemu",
      "Winner": 0
     },
     {
      "Year": 2022,
      "Category": "Best Action\/Adventure Game",
      "Game": "A Plague Tale: Requiem",
      "Studio": "Asobo Studio\/Focus Entertainment",
      "Winner": 0
     },
     {
      "Year": 2022,
      "Category": "Best Action\/Adventure Game",
      "Game": "God of War Ragnarök",
      "Studio": "Sony Santa Monica\/SIE",
      "Winner": 1
     },
     {
      "Year": 2022,
      "Category": "Best Action\/Adventure Game",
      "Game": "Horizon Forbidden West",
      "Studio": "Guerrilla Games\/SIE",
      "Winner": 0
     },
     {
      "Year": 2022,
      "Category": "Best Action\/Adventure Game",
      "Game": "Stray",
      "Studio": "BlueTwelve Studio\/Annapurna",
      "Winner": 0
     },
     {
      "Year": 2022,
      "Category": "Best Action\/Adventure Game",
      "Game": "TUNIC",
      "Studio": "TUNIC Team\/Finji",
      "Winner": 0
     },
     {
      "Year": 2022,
      "Category": "Best RPG",
      "Game": "Elden Ring",
      "Studio": "FromSoftware\/Bandai Namco",
      "Winner": 1
     },
     {
      "Year": 2022,
      "Category": "Best RPG",
      "Game": "Live a Live",
      "Studio": "Square Enix\/Nintendo",
      "Winner": 0
     },
     {
      "Year": 2022,
      "Category": "Best RPG",
      "Game": "Pokémon Legends: Arceus",
      "Studio": "Game Freak\/Nintendo\/TPCI",
      "Winner": 0
     },
     {
      "Year": 2022,
      "Category": "Best RPG",
      "Game": "Triangle Strategy",
      "Studio": "Artdink\/Square Enix",
      "Winner": 0
     },
     {
      "Year": 2022,
      "Category": "Best RPG",
      "Game": "Xenoblade Chronicles 3",
      "Studio": "Monolith Soft\/Nintendo",
      "Winner": 0
     },
     {
      "Year": 2022,
      "Category": "Best Fighting Game",
      "Game": "DNF Duel",
      "Studio": "Arc System Works\/EIGHTING\/NEOPLE\/NEXON",
      "Winner": 0
     },
     {
      "Year": 2022,
      "Category": "Best Fighting Game",
      "Game": "JoJo's Bizarre Adventure: All Star Battle R",
      "Studio": "CyberConnect 2 Co. Ltd\/Bandai Namco",
      "Winner": 0
     },
     {
      "Year": 2022,
      "Category": "Best Fighting Game",
      "Game": "The King of Fighters XV",
      "Studio": "SNK\/Plaion",
      "Winner": 0
     },
     {
      "Year": 2022,
      "Category": "Best Fighting Game",
      "Game": "MultiVersus",
      "Studio": "Player First Games\/WB Games",
      "Winner": 1
     },
     {
      "Year": 2022,
      "Category": "Best Fighting Game",
      "Game": "Sifu",
      "Studio": "Sloclap",
      "Winner": 0
     },
     {
      "Year": 2022,
      "Category": "Best Family Game",
      "Game": "Kirby and the Forgotten Land",
      "Studio": "HAL Laboratory \/ Nintendo",
      "Winner": 1
     },
     {
      "Year": 2022,
      "Category": "Best Family Game",
      "Game": "LEGO Star Wars: The Skywalker Saga",
      "Studio": "Traveller's Tales\/WB Games",
      "Winner": 0
     },
     {
      "Year": 2022,
      "Category": "Best Family Game",
      "Game": "Mario + Rabbids Sparks of Hope",
      "Studio": "Ubisoft Milan\/Paris\/Ubisoft",
      "Winner": 0
     },
     {
      "Year": 2022,
      "Category": "Best Family Game",
      "Game": "Nintendo Switch Sports",
      "Studio": "Nintendo",
      "Winner": 0
     },
     {
      "Year": 2022,
      "Category": "Best Family Game",
      "Game": "Splatoon 3",
      "Studio": "Nintendo",
      "Winner": 0
     },
     {
      "Year": 2022,
      "Category": "Best Sim\/Strategy Game",
      "Game": "Dune: Spice Wars",
      "Studio": "Shiro Games\/Funcom",
      "Winner": 0
     },
     {
      "Year": 2022,
      "Category": "Best Sim\/Strategy Game",
      "Game": "Mario + Rabbids Sparks of Hope",
      "Studio": "Ubisoft Milan\/Paris\/Ubisoft",
      "Winner": 1
     },
     {
      "Year": 2022,
      "Category": "Best Sim\/Strategy Game",
      "Game": "Total War: WARHAMMER III",
      "Studio": "Creative Assembly\/Sega",
      "Winner": 0
     },
     {
      "Year": 2022,
      "Category": "Best Sim\/Strategy Game",
      "Game": "Two Point Campus",
      "Studio": "Two Point Studios\/Sega",
      "Winner": 0
     },
     {
      "Year": 2022,
      "Category": "Best Sim\/Strategy Game",
      "Game": "Victoria 3",
      "Studio": "Paradox Development Studio\/Paradox Interactive",
      "Winner": 0
     },
     {
      "Year": 2022,
      "Category": "Best Sports\/Racing",
      "Game": "F1 22",
      "Studio": "Codemasters\/EA Sports",
      "Winner": 0
     },
     {
      "Year": 2022,
      "Category": "Best Sports\/Racing",
      "Game": "FIFA 23",
      "Studio": "EA Vancouver\/EA Romania\/EA Sports",
      "Winner": 0
     },
     {
      "Year": 2022,
      "Category": "Best Sports\/Racing",
      "Game": "NBA 2K23",
      "Studio": "Visual Concepts\/2K Sports",
      "Winner": 0
     },
     {
      "Year": 2022,
      "Category": "Best Sports\/Racing",
      "Game": "Gran Turismo 7",
      "Studio": "Polyphony Digital\/SIE",
      "Winner": 1
     },
     {
      "Year": 2022,
      "Category": "Best Sports\/Racing",
      "Game": "OlliOlli World",
      "Studio": "Roll 7\/Private Division",
      "Winner": 0
     },
     {
      "Year": 2022,
      "Category": "Best Multiplayer Present by Discord",
      "Game": "Call of Duty: Modern Warfare II",
      "Studio": "Infinity Ward\/Activision",
      "Winner": 0
     },
     {
      "Year": 2022,
      "Category": "Best Multiplayer Present by Discord",
      "Game": "MultiVersus",
      "Studio": "Player First Games\/WB Games",
      "Winner": 0
     },
     {
      "Year": 2022,
      "Category": "Best Multiplayer Present by Discord",
      "Game": "Overwatch 2",
      "Studio": "Blizzard Entertainment",
      "Winner": 0
     },
     {
      "Year": 2022,
      "Category": "Best Multiplayer Present by Discord",
      "Game": "Splatoon 3",
      "Studio": "Nintendo",
      "Winner": 1
     },
     {
      "Year": 2022,
      "Category": "Best Multiplayer Present by Discord",
      "Game": "Teenage Mutant Ninja Turtles: Shredder's Revenge",
      "Studio": "Tribute Games\/Dotemu",
      "Winner": 0
     },
     {
      "Year": 2022,
      "Category": "Most Anticipated Game",
      "Game": "FINAL FANTASY XVI",
      "Studio": "Square Enix",
      "Winner": 0
     },
     {
      "Year": 2022,
      "Category": "Most Anticipated Game",
      "Game": "Hogwarts Legacy",
      "Studio": "Avalanche Software\/WB Games",
      "Winner": 0
     },
     {
      "Year": 2022,
      "Category": "Most Anticipated Game",
      "Game": "Resident Evil 4",
      "Studio": "Capcom",
      "Winner": 0
     },
     {
      "Year": 2022,
      "Category": "Most Anticipated Game",
      "Game": "Starfield",
      "Studio": "Bethesda Game Studios\/Bethesda",
      "Winner": 0
     },
     {
      "Year": 2022,
      "Category": "Most Anticipated Game",
      "Game": "The Legend of Zelda: Tears of the Kingdom",
      "Studio": "Nintendo",
      "Winner": 1
     },
     {
      "Year": 2022,
      "Category": "Best eSports Game",
      "Game": "Counter-Strike: Global Offensive",
      "Studio": "Valve",
      "Winner": 0
     },
     {
      "Year": 2022,
      "Category": "Best eSports Game",
      "Game": "DOTA 2",
      "Studio": "Valve",
      "Winner": 0
     },
     {
      "Year": 2022,
      "Category": "Best eSports Game",
      "Game": "League of Legends",
      "Studio": "Riot Games",
      "Winner": 0
     },
     {
      "Year": 2022,
      "Category": "Best eSports Game",
      "Game": "Rocket League",
      "Studio": "Psyonix",
      "Winner": 0
     },
     {
      "Year": 2022,
      "Category": "Best eSports Game",
      "Game": "VALORANT",
      "Studio": "Riot Games",
      "Winner": 1
     },
     {
      "Year": 2022,
      "Category": "Innovation in Accessibility",
      "Game": "As Dusk Falls",
      "Studio": "Interior Night\/Xbox Game Studios",
      "Winner": 0
     },
     {
      "Year": 2022,
      "Category": "Innovation in Accessibility",
      "Game": "God of War Ragnarök",
      "Studio": "Sony Santa Monica\/SIE",
      "Winner": 1
     },
     {
      "Year": 2022,
      "Category": "Innovation in Accessibility",
      "Game": "Return to Monkey Island",
      "Studio": "Terrible Toybox\/Devolver Digital",
      "Winner": 0
     },
     {
      "Year": 2022,
      "Category": "Innovation in Accessibility",
      "Game": "The Last Of Us Part I",
      "Studio": "Naughty Dog \/ Sony Interactive Entertainment",
      "Winner": 0
     },
     {
      "Year": 2022,
      "Category": "Innovation in Accessibility",
      "Game": "The Quarry",
      "Studio": "Supermassive Games\/2K",
      "Winner": 0
     },
     {
      "Year": 2022,
      "Category": "Best Adaption",
      "Game": "Arcane: League of Legends",
      "Studio": "Fortiche\/Riot Games\/Netflix",
      "Winner": 1
     },
     {
      "Year": 2022,
      "Category": "Best Adaption",
      "Game": "Cyberpunk: Edgerunners",
      "Studio": "Studio Trigger\/CD Projekt, Netflix",
      "Winner": 0
     },
     {
      "Year": 2022,
      "Category": "Best Adaption",
      "Game": "The Cuphead Show!",
      "Studio": "Studio MDHR\/King Features Syndicate\/Netflix",
      "Winner": 0
     },
     {
      "Year": 2022,
      "Category": "Best Adaption",
      "Game": "Sonic the Hedgehog 2",
      "Studio": "Sega Sammy Group\/Paramount Pictures",
      "Winner": 0
     },
     {
      "Year": 2022,
      "Category": "Best Adaption",
      "Game": "Uncharted",
      "Studio": "PlayStation Productions\/Sony Pictures",
      "Winner": 0
     },
     {
      "Year": 2021,
      "Category": "Game of the Year",
      "Game": "Deathloop",
      "Studio": "Arkane Studios\/Bethesda",
      "Winner": 0
     },
     {
      "Year": 2021,
      "Category": "Game of the Year",
      "Game": "It Takes Two",
      "Studio": "Hazelight Studios\/EA",
      "Winner": 1
     },
     {
      "Year": 2021,
      "Category": "Game of the Year",
      "Game": "Metroid Dread",
      "Studio": "Mercury Steam\/Nintendo",
      "Winner": 0
     },
     {
      "Year": 2021,
      "Category": "Game of the Year",
      "Game": "Psychonauts 2",
      "Studio": "Double Fine\/Xbox Game Studios",
      "Winner": 0
     },
     {
      "Year": 2021,
      "Category": "Game of the Year",
      "Game": "Ratchet & Clank: Rift Apart",
      "Studio": "Insomniac Games\/SIE",
      "Winner": 0
     },
     {
      "Year": 2021,
      "Category": "Game of the Year",
      "Game": "Resident Evil Village",
      "Studio": "Capcom",
      "Winner": 0
     },
     {
      "Year": 2021,
      "Category": "Best Game Direction",
      "Game": "Deathloop",
      "Studio": "Arkane Studios\/Bethesda",
      "Winner": 1
     },
     {
      "Year": 2021,
      "Category": "Best Game Direction",
      "Game": "It Takes Two",
      "Studio": "Hazelight Studios\/EA",
      "Winner": 0
     },
     {
      "Year": 2021,
      "Category": "Best Game Direction",
      "Game": "Returnal",
      "Studio": "Housemarque\/SIE",
      "Winner": 0
     },
     {
      "Year": 2021,
      "Category": "Best Game Direction",
      "Game": "Psychonauts 2",
      "Studio": "Double Fine\/Xbox Game Studios",
      "Winner": 0
     },
     {
      "Year": 2021,
      "Category": "Best Game Direction",
      "Game": "Ratchet & Clank: Rift Apart",
      "Studio": "Insomniac Games\/SIE",
      "Winner": 0
     },
     {
      "Year": 2021,
      "Category": "Best Ongoing Game",
      "Game": "Apex Legends",
      "Studio": "Respawn Entertainment\/EA",
      "Winner": 0
     },
     {
      "Year": 2021,
      "Category": "Best Ongoing Game",
      "Game": "Call of Duty: Warzone",
      "Studio": "Infinity Ward \/ Raven \/ Activision",
      "Winner": 0
     },
     {
      "Year": 2021,
      "Category": "Best Ongoing Game",
      "Game": "Final Fantasy XIV Online",
      "Studio": "Square Enix",
      "Winner": 1
     },
     {
      "Year": 2021,
      "Category": "Best Ongoing Game",
      "Game": "Fortnite",
      "Studio": "Epic Games",
      "Winner": 0
     },
     {
      "Year": 2021,
      "Category": "Best Ongoing Game",
      "Game": "Genshin Impact",
      "Studio": "MiHoYo",
      "Winner": 0
     },
     {
      "Year": 2021,
      "Category": "Best Narrative",
      "Game": "Deathloop",
      "Studio": "Arkane Studios\/Bethesda",
      "Winner": 0
     },
     {
      "Year": 2021,
      "Category": "Best Narrative",
      "Game": "It Takes Two",
      "Studio": "Hazelight Studios\/EA",
      "Winner": 0
     },
     {
      "Year": 2021,
      "Category": "Best Narrative",
      "Game": "Life is Strange: True Colors",
      "Studio": "Deck Nine\/SQUARE ENIX",
      "Winner": 0
     },
     {
      "Year": 2021,
      "Category": "Best Narrative",
      "Game": "Marvel’s Guardians of the Galaxy",
      "Studio": "Eidos Montreal\/SQUARE ENIX",
      "Winner": 1
     },
     {
      "Year": 2021,
      "Category": "Best Narrative",
      "Game": "Psychonauts 2",
      "Studio": "Double Fine\/Xbox Game Studios",
      "Winner": 0
     },
     {
      "Year": 2021,
      "Category": "Best Independent Game",
      "Game": "12 Minutes",
      "Studio": "Luis Antonio\/Annapurna Interactive",
      "Winner": 0
     },
     {
      "Year": 2021,
      "Category": "Best Independent Game",
      "Game": "Death’s Door",
      "Studio": "Acid Nerve\/Devolver Digital",
      "Winner": 0
     },
     {
      "Year": 2021,
      "Category": "Best Independent Game",
      "Game": "Kena: Bridge of Spirits",
      "Studio": "Ember Lab",
      "Winner": 1
     },
     {
      "Year": 2021,
      "Category": "Best Independent Game",
      "Game": "Inscryption",
      "Studio": "Daniel Mullins Games\/Devolver Digital",
      "Winner": 0
     },
     {
      "Year": 2021,
      "Category": "Best Independent Game",
      "Game": "Loop Hero",
      "Studio": "Four Quarters\/Devolver Digital",
      "Winner": 0
     },
     {
      "Year": 2021,
      "Category": "Best Mobile Game",
      "Game": "Fantasian",
      "Studio": "Mistwalker",
      "Winner": 0
     },
     {
      "Year": 2021,
      "Category": "Best Mobile Game",
      "Game": "Genshin Impact",
      "Studio": "MiHoYo",
      "Winner": 1
     },
     {
      "Year": 2021,
      "Category": "Best Mobile Game",
      "Game": "League of Legends: Wild Rift",
      "Studio": "Riot Games",
      "Winner": 0
     },
     {
      "Year": 2021,
      "Category": "Best Mobile Game",
      "Game": "Marvel Future Revolution",
      "Studio": "Netmarble",
      "Winner": 0
     },
     {
      "Year": 2021,
      "Category": "Best Mobile Game",
      "Game": "Pokemon Unite",
      "Studio": "TiMi Studios\/The Pokemon Company",
      "Winner": 0
     },
     {
      "Year": 2021,
      "Category": "Best VR\/AR Game",
      "Game": "Hitman 3",
      "Studio": "IO Interactive",
      "Winner": 0
     },
     {
      "Year": 2021,
      "Category": "Best VR\/AR Game",
      "Game": "I Expect You To Die 2",
      "Studio": "Schell Games",
      "Winner": 0
     },
     {
      "Year": 2021,
      "Category": "Best VR\/AR Game",
      "Game": "Lone Echo II",
      "Studio": "Ready at Dawn\/Oculus Studios",
      "Winner": 0
     },
     {
      "Year": 2021,
      "Category": "Best VR\/AR Game",
      "Game": "Resident Evil 4",
      "Studio": "Armature Studio\/Capcom\/Oculus Studios",
      "Winner": 1
     },
     {
      "Year": 2021,
      "Category": "Best VR\/AR Game",
      "Game": "Sniper Elite VR",
      "Studio": "Coatsink\/Just Add Water\/Rebellion Developments",
      "Winner": 0
     },
     {
      "Year": 2021,
      "Category": "Best Action",
      "Game": "Back 4 Blood",
      "Studio": "Turtle Rock\/WB Games",
      "Winner": 0
     },
     {
      "Year": 2021,
      "Category": "Best Action",
      "Game": "Chivalry II",
      "Studio": "Torn Banner Studios\/Tripwire Interactive",
      "Winner": 0
     },
     {
      "Year": 2021,
      "Category": "Best Action",
      "Game": "Deathloop",
      "Studio": "Arkane Studios\/Bethesda",
      "Winner": 0
     },
     {
      "Year": 2021,
      "Category": "Best Action",
      "Game": "Far Cry 6",
      "Studio": "Ubisoft Toronto\/Ubisoft",
      "Winner": 0
     },
     {
      "Year": 2021,
      "Category": "Best Action",
      "Game": "Returnal",
      "Studio": "Housemarque\/SIE",
      "Winner": 1
     },
     {
      "Year": 2021,
      "Category": "Best Action\/Adventure Game",
      "Game": "Marvel’s Guardians of the Galaxy",
      "Studio": "Eidos Montreal\/SQUARE ENIX",
      "Winner": 0
     },
     {
      "Year": 2021,
      "Category": "Best Action\/Adventure Game",
      "Game": "Metroid Dread",
      "Studio": "Mercury Steam\/Nintendo",
      "Winner": 1
     },
     {
      "Year": 2021,
      "Category": "Best Action\/Adventure Game",
      "Game": "Psychonauts 2",
      "Studio": "Double Fine\/Xbox Game Studios",
      "Winner": 0
     },
     {
      "Year": 2021,
      "Category": "Best Action\/Adventure Game",
      "Game": "Ratchet & Clank: Rift Apart",
      "Studio": "Insomniac Games\/SIE",
      "Winner": 0
     },
     {
      "Year": 2021,
      "Category": "Best Action\/Adventure Game",
      "Game": "Resident Evil Village",
      "Studio": "Capcom",
      "Winner": 0
     },
     {
      "Year": 2021,
      "Category": "Best RPG",
      "Game": "Cyberpunk 2077",
      "Studio": "CD Projekt Red",
      "Winner": 0
     },
     {
      "Year": 2021,
      "Category": "Best RPG",
      "Game": "Monster Hunter Rise",
      "Studio": "Capcom",
      "Winner": 0
     },
     {
      "Year": 2021,
      "Category": "Best RPG",
      "Game": "Scarlet Nexus",
      "Studio": "Bandai Namco",
      "Winner": 0
     },
     {
      "Year": 2021,
      "Category": "Best RPG",
      "Game": "Shin Megami Tensei V",
      "Studio": "Atlus\/Sega",
      "Winner": 0
     },
     {
      "Year": 2021,
      "Category": "Best RPG",
      "Game": "Tales of Arise",
      "Studio": "Bandai Namco",
      "Winner": 1
     },
     {
      "Year": 2021,
      "Category": "Best Fighting Game",
      "Game": "Demon Slayer -Kimetsu no Yaiba- The Hinokami Chronicles",
      "Studio": "CyberConnect2\/Sega",
      "Winner": 0
     },
     {
      "Year": 2021,
      "Category": "Best Fighting Game",
      "Game": "Guilty Gear -Strive-",
      "Studio": "Arc System Works",
      "Winner": 1
     },
     {
      "Year": 2021,
      "Category": "Best Fighting Game",
      "Game": "Melty Blood: Type Lumina",
      "Studio": "French-Bread\/Delightworks",
      "Winner": 0
     },
     {
      "Year": 2021,
      "Category": "Best Fighting Game",
      "Game": "Nickelodeon All-Star Brawl",
      "Studio": "Ludosity\/Fair Play Labs\/GameMill",
      "Winner": 0
     },
     {
      "Year": 2021,
      "Category": "Best Fighting Game",
      "Game": "Virtua Fighter 5: Ultimate Showdown",
      "Studio": "Sega",
      "Winner": 0
     },
     {
      "Year": 2021,
      "Category": "Best Debut Indie Game",
      "Game": "Kena: Bridge of Spirits",
      "Studio": "Ember Lab",
      "Winner": 1
     },
     {
      "Year": 2021,
      "Category": "Best Debut Indie Game",
      "Game": "Sable",
      "Studio": "Shedworks\/Raw Fury",
      "Winner": 0
     },
     {
      "Year": 2021,
      "Category": "Best Debut Indie Game",
      "Game": "The Artful Escape",
      "Studio": "Beethoven & Dinosaur\/Annapurna",
      "Winner": 0
     },
     {
      "Year": 2021,
      "Category": "Best Debut Indie Game",
      "Game": "The Forgotten City",
      "Studio": "Modern Storyteller\/Dear Villagers",
      "Winner": 0
     },
     {
      "Year": 2021,
      "Category": "Best Debut Indie Game",
      "Game": "Valheim",
      "Studio": "Iron Gate\/Coffee Stain",
      "Winner": 0
     },
     {
      "Year": 2021,
      "Category": "Best Family Game",
      "Game": "It Takes Two",
      "Studio": "Hazelight Studios\/EA",
      "Winner": 1
     },
     {
      "Year": 2021,
      "Category": "Best Family Game",
      "Game": "Mario Party Superstars",
      "Studio": "NDcube\/Nintendo",
      "Winner": 0
     },
     {
      "Year": 2021,
      "Category": "Best Family Game",
      "Game": "New Pokémon Snap",
      "Studio": "Bandai Namco\/The Pokémon Company\/Nintendo",
      "Winner": 0
     },
     {
      "Year": 2021,
      "Category": "Best Family Game",
      "Game": "Super Mario 3D World + Bowser’s Fury",
      "Studio": "Nintendo",
      "Winner": 0
     },
     {
      "Year": 2021,
      "Category": "Best Family Game",
      "Game": "WarioWare: Get It Together!",
      "Studio": "Intelligent Systems\/Nintendo",
      "Winner": 0
     },
     {
      "Year": 2021,
      "Category": "Best Sports\/Racing",
      "Game": "F1 2021",
      "Studio": "Codemasters\/EA Sports",
      "Winner": 0
     },
     {
      "Year": 2021,
      "Category": "Best Sports\/Racing",
      "Game": "FIFA 22",
      "Studio": "EA Vancouver\/EA Sports",
      "Winner": 0
     },
     {
      "Year": 2021,
      "Category": "Best Sports\/Racing",
      "Game": "Forza Horizon 5",
      "Studio": "Playground Games\/Xbox Game Studios",
      "Winner": 1
     },
     {
      "Year": 2021,
      "Category": "Best Sports\/Racing",
      "Game": "Hot Wheels Unleashed",
      "Studio": "Milestone",
      "Winner": 0
     },
     {
      "Year": 2021,
      "Category": "Best Sports\/Racing",
      "Game": "Riders Republic",
      "Studio": "Ubisoft Annecy\/Ubisoft",
      "Winner": 0
     },
     {
      "Year": 2021,
      "Category": "Best Sim\/Strategy Game",
      "Game": "Age of Empires IV",
      "Studio": "Relic Entertainment\/Xbox Game Studios",
      "Winner": 1
     },
     {
      "Year": 2021,
      "Category": "Best Sim\/Strategy Game",
      "Game": "Evil Genius 2: World Domination",
      "Studio": "Rebellion Developments",
      "Winner": 0
     },
     {
      "Year": 2021,
      "Category": "Best Sim\/Strategy Game",
      "Game": "Humankind",
      "Studio": "Amplitude Studios\/Sega",
      "Winner": 0
     },
     {
      "Year": 2021,
      "Category": "Best Sim\/Strategy Game",
      "Game": "Inscryption",
      "Studio": "Daniel Mullins Games\/Devolver",
      "Winner": 0
     },
     {
      "Year": 2021,
      "Category": "Best Sim\/Strategy Game",
      "Game": "Microsoft Flight Simulator",
      "Studio": "Asobo Studio\/Xbox Game Studios",
      "Winner": 0
     },
     {
      "Year": 2021,
      "Category": "Best Multiplayer Present by Discord",
      "Game": "Back 4 Blood",
      "Studio": "Turtle Rock\/WB Games",
      "Winner": 0
     },
     {
      "Year": 2021,
      "Category": "Best Multiplayer Present by Discord",
      "Game": "It Takes Two",
      "Studio": "Hazelight Studios\/EA",
      "Winner": 1
     },
     {
      "Year": 2021,
      "Category": "Best Multiplayer Present by Discord",
      "Game": "Knockout City",
      "Studio": "Velan Studios\/EA",
      "Winner": 0
     },
     {
      "Year": 2021,
      "Category": "Best Multiplayer Present by Discord",
      "Game": "Monster Hunter Rise",
      "Studio": "Capcom",
      "Winner": 0
     },
     {
      "Year": 2021,
      "Category": "Best Multiplayer Present by Discord",
      "Game": "New World",
      "Studio": "Amazon Games",
      "Winner": 0
     },
     {
      "Year": 2021,
      "Category": "Best Multiplayer Present by Discord",
      "Game": "Valheim",
      "Studio": "Iron Gate\/Coffee Stain",
      "Winner": 0
     },
     {
      "Year": 2021,
      "Category": "Most Anticipated Game",
      "Game": "Elden Ring",
      "Studio": "FromSoftware\/Bandai Namco",
      "Winner": 1
     },
     {
      "Year": 2021,
      "Category": "Most Anticipated Game",
      "Game": "God of War Ragnarök",
      "Studio": "Sony Santa Monica\/SIE",
      "Winner": 0
     },
     {
      "Year": 2021,
      "Category": "Most Anticipated Game",
      "Game": "Horizon Forbidden West",
      "Studio": "Guerrilla Games\/SIE",
      "Winner": 0
     },
     {
      "Year": 2021,
      "Category": "Most Anticipated Game",
      "Game": "Sequel to The Legend of Zelda: Breath of the Wild",
      "Studio": "Nintendo",
      "Winner": 0
     },
     {
      "Year": 2021,
      "Category": "Most Anticipated Game",
      "Game": "Starfield",
      "Studio": "Bethesda Game Studios\/Bethesda",
      "Winner": 0
     },
     {
      "Year": 2021,
      "Category": "Best Art Direction",
      "Game": "Deathloop",
      "Studio": "Arkane Studios\/Bethesda",
      "Winner": 1
     },
     {
      "Year": 2021,
      "Category": "Best Art Direction",
      "Game": "Kena: Bridge of Spirits",
      "Studio": "Ember Lab",
      "Winner": 0
     },
     {
      "Year": 2021,
      "Category": "Best Art Direction",
      "Game": "Psychonauts 2",
      "Studio": "Double Fine\/Xbox Game Studios",
      "Winner": 0
     },
     {
      "Year": 2021,
      "Category": "Best Art Direction",
      "Game": "Ratchet & Clank: Rift Apart",
      "Studio": "Insomniac Games\/SIE",
      "Winner": 0
     },
     {
      "Year": 2021,
      "Category": "Best Art Direction",
      "Game": "The Artful Escape",
      "Studio": "Beethoven & Dinosaur\/Annapurna",
      "Winner": 0
     },
     {
      "Year": 2021,
      "Category": "Best Score and Music",
      "Game": "Cyberpunk 2077",
      "Studio": "Marcin Przybylowicz, Piotr T. Adamczyk, Composers",
      "Winner": 0
     },
     {
      "Year": 2021,
      "Category": "Best Score and Music",
      "Game": "Deathloop",
      "Studio": "Tom Salta, Composer",
      "Winner": 0
     },
     {
      "Year": 2021,
      "Category": "Best Score and Music",
      "Game": "NieR Replicant ver.1.22474487139",
      "Studio": "Keiichi Okabe, Composer",
      "Winner": 1
     },
     {
      "Year": 2021,
      "Category": "Best Score and Music",
      "Game": "Marvel’s Guardians of the Galaxy",
      "Studio": "Richard Jacques, Composer",
      "Winner": 0
     },
     {
      "Year": 2021,
      "Category": "Best Score and Music",
      "Game": "The Artful Escape",
      "Studio": "Johnny Galvatron & Josh Abrahams, Composers",
      "Winner": 0
     },
     {
      "Year": 2021,
      "Category": "Best Audio Design",
      "Game": "Deathloop",
      "Studio": "Arkane Studios\/Bethesda",
      "Winner": 0
     },
     {
      "Year": 2021,
      "Category": "Best Audio Design",
      "Game": "Forza Horizon 5",
      "Studio": "Playground Games\/Xbox Game Studios",
      "Winner": 1
     },
     {
      "Year": 2021,
      "Category": "Best Audio Design",
      "Game": "Ratchet & Clank: Rift Apart",
      "Studio": "Insomniac Games\/SIE",
      "Winner": 0
     },
     {
      "Year": 2021,
      "Category": "Best Audio Design",
      "Game": "Resident Evil Village",
      "Studio": "Capcom",
      "Winner": 0
     },
     {
      "Year": 2021,
      "Category": "Best Audio Design",
      "Game": "Returnal",
      "Studio": "Housemarque\/SIE",
      "Winner": 0
     },
     {
      "Year": 2021,
      "Category": "Games for Impact",
      "Game": "Before Your Eyes",
      "Studio": "GoodbyeWorld Games\/Skybound Games",
      "Winner": 0
     },
     {
      "Year": 2021,
      "Category": "Games for Impact",
      "Game": "Boyfriend Dungeon",
      "Studio": "Kitfox Games",
      "Winner": 0
     },
     {
      "Year": 2021,
      "Category": "Games for Impact",
      "Game": "Chicory",
      "Studio": "Greg Lobanow, Alexis dean-Jones, Lena Raine, Madeline Berger, A Shell in the Pit\/Finji",
      "Winner": 0
     },
     {
      "Year": 2021,
      "Category": "Games for Impact",
      "Game": "Life is Strange: True Colors",
      "Studio": "Deck Nine\/SQUARE ENIX",
      "Winner": 1
     },
     {
      "Year": 2021,
      "Category": "Games for Impact",
      "Game": "No Longer Home",
      "Studio": "Humble Grove, Hana Lee, Cel Davison, Adrienne Lombardo, Eli Rainsberry\/Fellow Traveler",
      "Winner": 0
     },
     {
      "Year": 2021,
      "Category": "Best Community Support",
      "Game": "Apex Legends",
      "Studio": "Respawn Entertainment\/EA",
      "Winner": 0
     },
     {
      "Year": 2021,
      "Category": "Best Community Support",
      "Game": "Destiny 2",
      "Studio": "Bungie",
      "Winner": 0
     },
     {
      "Year": 2021,
      "Category": "Best Community Support",
      "Game": "Final Fantasy XIV Online",
      "Studio": "Square Enix",
      "Winner": 1
     },
     {
      "Year": 2021,
      "Category": "Best Community Support",
      "Game": "Fortnite",
      "Studio": "Epic Games",
      "Winner": 0
     },
     {
      "Year": 2021,
      "Category": "Best Community Support",
      "Game": "No Man’s Sky",
      "Studio": "Hello Games",
      "Winner": 0
     },
     {
      "Year": 2021,
      "Category": "Innovation in Accessibility",
      "Game": "Far Cry 6",
      "Studio": "Ubisoft Toronto\/Ubisoft",
      "Winner": 0
     },
     {
      "Year": 2021,
      "Category": "Innovation in Accessibility",
      "Game": "Forza Horizon 5",
      "Studio": "Playground Games\/Xbox Game Studios",
      "Winner": 1
     },
     {
      "Year": 2021,
      "Category": "Innovation in Accessibility",
      "Game": "Marvel’s Guardians of the Galaxy",
      "Studio": "Eidos Montreal\/SQUARE ENIX",
      "Winner": 0
     },
     {
      "Year": 2021,
      "Category": "Innovation in Accessibility",
      "Game": "Ratchet & Clank: Rift Apart",
      "Studio": "Insomniac Games\/SIE",
      "Winner": 0
     },
     {
      "Year": 2021,
      "Category": "Innovation in Accessibility",
      "Game": "The Vale: Shadow of the Crown",
      "Studio": "Creative Bytes Studios\/Falling Squirrel",
      "Winner": 0
     },
     {
      "Year": 2021,
      "Category": "Best eSports Game",
      "Game": "Call of Duty",
      "Studio": "Activision",
      "Winner": 0
     },
     {
      "Year": 2021,
      "Category": "Best eSports Game",
      "Game": "CS:GO",
      "Studio": "Valve",
      "Winner": 0
     },
     {
      "Year": 2021,
      "Category": "Best eSports Game",
      "Game": "DOTA2",
      "Studio": "Valve",
      "Winner": 0
     },
     {
      "Year": 2021,
      "Category": "Best eSports Game",
      "Game": "League of Legends",
      "Studio": "Riot Games",
      "Winner": 1
     },
     {
      "Year": 2021,
      "Category": "Best eSports Game",
      "Game": "Valorant",
      "Studio": "Riot Games",
      "Winner": 0
     },
     {
      "Year": 2020,
      "Category": "Game of the Year",
      "Game": "The Last of Us Part II",
      "Studio": "Naughty Dog \/ Sony Interactive Entertainment",
      "Winner": 1
     },
     {
      "Year": 2020,
      "Category": "Game of the Year",
      "Game": "Animal Crossing: New Horizons",
      "Studio": "Nintendo",
      "Winner": 0
     },
     {
      "Year": 2020,
      "Category": "Game of the Year",
      "Game": "Doom Eternal",
      "Studio": "id Software",
      "Winner": 0
     },
     {
      "Year": 2020,
      "Category": "Game of the Year",
      "Game": "Final Fantasy VII Remake",
      "Studio": "Square Enix",
      "Winner": 0
     },
     {
      "Year": 2020,
      "Category": "Game of the Year",
      "Game": "Ghost of Tsushima",
      "Studio": "Sucker Punch Productions \/ Sony Interactive Entertainment",
      "Winner": 0
     },
     {
      "Year": 2020,
      "Category": "Game of the Year",
      "Game": "Hades",
      "Studio": "Supergiant Games",
      "Winner": 0
     },
     {
      "Year": 2020,
      "Category": "Best Game Direction",
      "Game": "The Last of Us Part II",
      "Studio": "Naughty Dog \/ Sony Interactive Entertainment",
      "Winner": 1
     },
     {
      "Year": 2020,
      "Category": "Best Game Direction",
      "Game": "Final Fantasy VII Remake",
      "Studio": "Square Enix",
      "Winner": 0
     },
     {
      "Year": 2020,
      "Category": "Best Game Direction",
      "Game": "Ghost of Tsushima",
      "Studio": "Sucker Punch Productions \/ Sony Interactive Entertainment",
      "Winner": 0
     },
     {
      "Year": 2020,
      "Category": "Best Game Direction",
      "Game": "Hades",
      "Studio": "Supergiant Games",
      "Winner": 0
     },
     {
      "Year": 2020,
      "Category": "Best Game Direction",
      "Game": "Half-Life Alyx",
      "Studio": "Valve",
      "Winner": 0
     },
     {
      "Year": 2020,
      "Category": "Most Anticipated Game",
      "Game": "Elden Ring",
      "Studio": "FromSoftware\/Bandai Namco",
      "Winner": 1
     },
     {
      "Year": 2020,
      "Category": "Most Anticipated Game",
      "Game": "Halo Infinite",
      "Studio": "343 Industries \/ Xbox Game Studios",
      "Winner": 0
     },
     {
      "Year": 2020,
      "Category": "Most Anticipated Game",
      "Game": "Horizon Forbidden West",
      "Studio": "Guerrilla Games\/SIE",
      "Winner": 0
     },
     {
      "Year": 2020,
      "Category": "Most Anticipated Game",
      "Game": "God of War Sequel",
      "Studio": "SIE Santa Monica\/SIE",
      "Winner": 0
     },
     {
      "Year": 2020,
      "Category": "Most Anticipated Game",
      "Game": "Resident Evil Village",
      "Studio": "Capcom",
      "Winner": 0
     },
     {
      "Year": 2020,
      "Category": "Most Anticipated Game",
      "Game": "The Legend of Zelda: Breath of the Wild Sequel",
      "Studio": "Nintendo",
      "Winner": 0
     },
     {
      "Year": 2020,
      "Category": "Best Narrative",
      "Game": "The Last of Us Part II",
      "Studio": "Naughty Dog \/ Sony Interactive Entertainment",
      "Winner": 1
     },
     {
      "Year": 2020,
      "Category": "Best Narrative",
      "Game": "13 Sentinels: Aegis Rim",
      "Studio": "Aegis Rim",
      "Winner": 0
     },
     {
      "Year": 2020,
      "Category": "Best Narrative",
      "Game": "Final Fantasy VII Remake",
      "Studio": "Square Enix",
      "Winner": 0
     },
     {
      "Year": 2020,
      "Category": "Best Narrative",
      "Game": "Ghost of Tsushima",
      "Studio": "Sucker Punch Productions \/ Sony Interactive Entertainment",
      "Winner": 0
     },
     {
      "Year": 2020,
      "Category": "Best Narrative",
      "Game": "Hades",
      "Studio": "Supergiant Games",
      "Winner": 0
     },
     {
      "Year": 2020,
      "Category": "Best Art Direction",
      "Game": "Ghost of Tsushima",
      "Studio": "Sucker Punch Productions \/ Sony Interactive Entertainment",
      "Winner": 1
     },
     {
      "Year": 2020,
      "Category": "Best Art Direction",
      "Game": "Final Fantasy VII Remake",
      "Studio": "Square Enix",
      "Winner": 0
     },
     {
      "Year": 2020,
      "Category": "Best Art Direction",
      "Game": "Hades",
      "Studio": "Supergiant Games",
      "Winner": 0
     },
     {
      "Year": 2020,
      "Category": "Best Art Direction",
      "Game": "The Last of Us Part II",
      "Studio": "Naughty Dog \/ Sony Interactive Entertainment",
      "Winner": 0
     },
     {
      "Year": 2020,
      "Category": "Best Art Direction",
      "Game": "Ori and the Will of the Wisps",
      "Studio": "Moon Studios \/ Xbox Game Studios",
      "Winner": 0
     },
     {
      "Year": 2020,
      "Category": "Best Score and Music",
      "Game": "Final Fantasy VII Remake",
      "Studio": "Nobuo Uematsu, Masashi Hamauzu, and Mitsuto Suzuki",
      "Winner": 1
     },
     {
      "Year": 2020,
      "Category": "Best Score and Music",
      "Game": "Doom Eternal",
      "Studio": "Mick Gordon",
      "Winner": 0
     },
     {
      "Year": 2020,
      "Category": "Best Score and Music",
      "Game": "Hades",
      "Studio": "Darren Korb",
      "Winner": 0
     },
     {
      "Year": 2020,
      "Category": "Best Score and Music",
      "Game": "The Last of Us Part II",
      "Studio": "Gustavo Santaolalla and Mac Quayle",
      "Winner": 0
     },
     {
      "Year": 2020,
      "Category": "Best Score and Music",
      "Game": "Ori and the Will of the Wisps",
      "Studio": "Gareth Coker",
      "Winner": 0
     },
     {
      "Year": 2020,
      "Category": "Best Audio Design",
      "Game": "The Last of Us Part II",
      "Studio": "Naughty Dog \/ Sony Interactive Entertainment",
      "Winner": 1
     },
     {
      "Year": 2020,
      "Category": "Best Audio Design",
      "Game": "Doom Eternal",
      "Studio": "id Software \/ Bethesda Softworks",
      "Winner": 0
     },
     {
      "Year": 2020,
      "Category": "Best Audio Design",
      "Game": "Ghost of Tsushima",
      "Studio": "Sucker Punch Productions \/ Sony Interactive Entertainment",
      "Winner": 0
     },
     {
      "Year": 2020,
      "Category": "Best Audio Design",
      "Game": "Half-Life: Alyx",
      "Studio": "Valve",
      "Winner": 0
     },
     {
      "Year": 2020,
      "Category": "Best Audio Design",
      "Game": "Resident Evil 3",
      "Studio": "Capcom",
      "Winner": 0
     },
     {
      "Year": 2020,
      "Category": "Games for Impact",
      "Game": "Tell Me Why",
      "Studio": "Dontnod Entertainment \/ Xbox Game Studios",
      "Winner": 1
     },
     {
      "Year": 2020,
      "Category": "Games for Impact",
      "Game": "If Found...",
      "Studio": "Dreamfeel \/ Annapurna Interactive",
      "Winner": 0
     },
     {
      "Year": 2020,
      "Category": "Games for Impact",
      "Game": "Kentucky Route Zero",
      "Studio": "Cardboard Computer \/ Annapurna Interactive",
      "Winner": 0
     },
     {
      "Year": 2020,
      "Category": "Games for Impact",
      "Game": "Spiritfarer",
      "Studio": "Thunder Lotus Games",
      "Winner": 0
     },
     {
      "Year": 2020,
      "Category": "Games for Impact",
      "Game": "Through the Darkest of Times",
      "Studio": "Paintbucket Games \/ HandyGames",
      "Winner": 0
     },
     {
      "Year": 2020,
      "Category": "Best Ongoing Game",
      "Game": "No Man's Sky",
      "Studio": "Hello Games",
      "Winner": 1
     },
     {
      "Year": 2020,
      "Category": "Best Ongoing Game",
      "Game": "Apex Legends",
      "Studio": "Respawn Entertainment\/EA",
      "Winner": 0
     },
     {
      "Year": 2020,
      "Category": "Best Ongoing Game",
      "Game": "Call of Duty: Warzone",
      "Studio": "Infinity Ward \/ Raven Software \/ Activision",
      "Winner": 0
     },
     {
      "Year": 2020,
      "Category": "Best Ongoing Game",
      "Game": "Destiny 2",
      "Studio": "Bungie",
      "Winner": 0
     },
     {
      "Year": 2020,
      "Category": "Best Ongoing Game",
      "Game": "Fortnite",
      "Studio": "Epic Games",
      "Winner": 0
     },
     {
      "Year": 2020,
      "Category": "Best Independent Game",
      "Game": "Hades",
      "Studio": "Supergiant Games",
      "Winner": 1
     },
     {
      "Year": 2020,
      "Category": "Best Independent Game",
      "Game": "Carrion",
      "Studio": "Phobia Game Studio \/ Devolver Digital",
      "Winner": 0
     },
     {
      "Year": 2020,
      "Category": "Best Independent Game",
      "Game": "Fall Guys",
      "Studio": "Mediatonic \/ Devolver Digital",
      "Winner": 0
     },
     {
      "Year": 2020,
      "Category": "Best Independent Game",
      "Game": "Spelunky 2",
      "Studio": "Mossmouth",
      "Winner": 0
     },
     {
      "Year": 2020,
      "Category": "Best Independent Game",
      "Game": "Spiritfarer",
      "Studio": "Thunder Lotus Games",
      "Winner": 0
     },
     {
      "Year": 2020,
      "Category": "Best Mobile Game",
      "Game": "Among Us",
      "Studio": "Innersloth",
      "Winner": 1
     },
     {
      "Year": 2020,
      "Category": "Best Mobile Game",
      "Game": "Call of Duty: Mobile",
      "Studio": "TiMi Studios \/ Activision",
      "Winner": 0
     },
     {
      "Year": 2020,
      "Category": "Best Mobile Game",
      "Game": "Genshin Impact",
      "Studio": "miHoYo",
      "Winner": 0
     },
     {
      "Year": 2020,
      "Category": "Best Mobile Game",
      "Game": "Legends of Runeterra",
      "Studio": "Riot Games",
      "Winner": 0
     },
     {
      "Year": 2020,
      "Category": "Best Mobile Game",
      "Game": "Pokémon Café Mix",
      "Studio": "Genius Sonority \/ The Pokémon Company",
      "Winner": 0
     },
     {
      "Year": 2020,
      "Category": "Best Community Support",
      "Game": "Fall Guys",
      "Studio": "Mediatonic \/ Devolver Digital",
      "Winner": 1
     },
     {
      "Year": 2020,
      "Category": "Best Community Support",
      "Game": "Apex Legends",
      "Studio": "Respawn Entertainment\/EA",
      "Winner": 0
     },
     {
      "Year": 2020,
      "Category": "Best Community Support",
      "Game": "Destiny 2",
      "Studio": "Bungie",
      "Winner": 0
     },
     {
      "Year": 2020,
      "Category": "Best Community Support",
      "Game": "Fortnite",
      "Studio": "Epic Games",
      "Winner": 0
     },
     {
      "Year": 2020,
      "Category": "Best Community Support",
      "Game": "No Man's Sky",
      "Studio": "Hello Games",
      "Winner": 0
     },
     {
      "Year": 2020,
      "Category": "Best Community Support",
      "Game": "Valorant",
      "Studio": "Riot Games",
      "Winner": 0
     },
     {
      "Year": 2020,
      "Category": "Best VR\/AR Game",
      "Game": "Half-Life: Alyx",
      "Studio": "Valve",
      "Winner": 1
     },
     {
      "Year": 2020,
      "Category": "Best VR\/AR Game",
      "Game": "Dreams",
      "Studio": "Media Molecule \/ Sony Interactive Entertainment",
      "Winner": 0
     },
     {
      "Year": 2020,
      "Category": "Best VR\/AR Game",
      "Game": "Iron Man VR",
      "Studio": "Camouflaj \/ Sony Interactive Entertainment",
      "Winner": 0
     },
     {
      "Year": 2020,
      "Category": "Best VR\/AR Game",
      "Game": "Star Wars Squadrons",
      "Studio": "Motive Studio\/EA",
      "Winner": 0
     },
     {
      "Year": 2020,
      "Category": "Best VR\/AR Game",
      "Game": "The Walking Dead: Saints & Sinners",
      "Studio": "Skydance Interactive",
      "Winner": 0
     },
     {
      "Year": 2020,
      "Category": "Innovation in Accessibility",
      "Game": "The Last of Us Part II",
      "Studio": "Naughty Dog \/ Sony Interactive Entertainment",
      "Winner": 1
     },
     {
      "Year": 2020,
      "Category": "Innovation in Accessibility",
      "Game": "Assassin's Creed Valhalla",
      "Studio": "Ubisoft Montreal \/ Ubisoft",
      "Winner": 0
     },
     {
      "Year": 2020,
      "Category": "Innovation in Accessibility",
      "Game": "Grounded",
      "Studio": "Obsidian Entertainment \/ Xbox Game Studios",
      "Winner": 0
     },
     {
      "Year": 2020,
      "Category": "Innovation in Accessibility",
      "Game": "HyperDot",
      "Studio": "Tribe Games \/ GLITCH",
      "Winner": 0
     },
     {
      "Year": 2020,
      "Category": "Innovation in Accessibility",
      "Game": "Watch Dogs Legion",
      "Studio": "Ubisoft Toronto\/Ubisoft",
      "Winner": 0
     },
     {
      "Year": 2020,
      "Category": "Best Action Game",
      "Game": "Hades",
      "Studio": "Supergiant Games",
      "Winner": 1
     },
     {
      "Year": 2020,
      "Category": "Best Action Game",
      "Game": "Doom Eternal",
      "Studio": "id Software \/ Bethesda Softworks",
      "Winner": 0
     },
     {
      "Year": 2020,
      "Category": "Best Action Game",
      "Game": "Half-Life: Alyx",
      "Studio": "Valve",
      "Winner": 0
     },
     {
      "Year": 2020,
      "Category": "Best Action Game",
      "Game": "Nioh 2",
      "Studio": "Team Ninja",
      "Winner": 0
     },
     {
      "Year": 2020,
      "Category": "Best Action Game",
      "Game": "Streets of Rage 4",
      "Studio": "Dotemu",
      "Winner": 0
     },
     {
      "Year": 2020,
      "Category": "Best Action\/Adventure Game",
      "Game": "The Last of Us Part II",
      "Studio": "Naughty Dog \/ Sony Interactive Entertainment",
      "Winner": 1
     },
     {
      "Year": 2020,
      "Category": "Best Action\/Adventure Game",
      "Game": "Assassin's Creed Valhalla",
      "Studio": "Ubisoft Montreal \/ Ubisoft",
      "Winner": 0
     },
     {
      "Year": 2020,
      "Category": "Best Action\/Adventure Game",
      "Game": "Ghost of Tsushima",
      "Studio": "Sucker Punch Productions \/ Sony Interactive Entertainment",
      "Winner": 0
     },
     {
      "Year": 2020,
      "Category": "Best Action\/Adventure Game",
      "Game": "Ori and the Will of the Wisps",
      "Studio": "Moon Studios \/ Xbox Game Studios",
      "Winner": 0
     },
     {
      "Year": 2020,
      "Category": "Best Action\/Adventure Game",
      "Game": "Spider-Man: Miles Morales",
      "Studio": "Insomniac Games\/SIE",
      "Winner": 0
     },
     {
      "Year": 2020,
      "Category": "Best Action\/Adventure Game",
      "Game": "Star Wars Jedi: Fallen Order",
      "Studio": "Respawn Entertainment\/EA",
      "Winner": 0
     },
     {
      "Year": 2020,
      "Category": "Best RPG",
      "Game": "Final Fantasy VII Remake",
      "Studio": "Square Enix",
      "Winner": 1
     },
     {
      "Year": 2020,
      "Category": "Best RPG",
      "Game": "Genshin Impact",
      "Studio": "miHoYo",
      "Winner": 0
     },
     {
      "Year": 2020,
      "Category": "Best RPG",
      "Game": "Persona 5 Royal",
      "Studio": "Atlus\/Sega",
      "Winner": 0
     },
     {
      "Year": 2020,
      "Category": "Best RPG",
      "Game": "Wasteland 3",
      "Studio": "inXile Entertainment \/ Deep Silver",
      "Winner": 0
     },
     {
      "Year": 2020,
      "Category": "Best RPG",
      "Game": "Yakuza: Like a Dragon",
      "Studio": "Ryu Ga Gotoku Studio\/Sega",
      "Winner": 0
     },
     {
      "Year": 2020,
      "Category": "Best Fighting Game",
      "Game": "Mortal Kombat 11: Ultimate Edition",
      "Studio": "NetherRealm Studios\/WB Games",
      "Winner": 1
     },
     {
      "Year": 2020,
      "Category": "Best Fighting Game",
      "Game": "Granblue Fantasy Versus",
      "Studio": "Arc System Works \/ Cygames \/ Xseed Games",
      "Winner": 0
     },
     {
      "Year": 2020,
      "Category": "Best Fighting Game",
      "Game": "One-Punch Man: A Hero Nobody Knows",
      "Studio": "Spike Chunsoft \/ Bandai Namco",
      "Winner": 0
     },
     {
      "Year": 2020,
      "Category": "Best Fighting Game",
      "Game": "Street Fighter V Champion Edition",
      "Studio": "Dimps \/ Capcom",
      "Winner": 0
     },
     {
      "Year": 2020,
      "Category": "Best Fighting Game",
      "Game": "Under Night In-Birth Exe:Late[cl-r]",
      "Studio": "French Bread \/ Arc System Works \/ Aksys",
      "Winner": 0
     },
     {
      "Year": 2020,
      "Category": "Best Family Game",
      "Game": "Animal Crossing: New Horizons",
      "Studio": "Nintendo",
      "Winner": 1
     },
     {
      "Year": 2020,
      "Category": "Best Family Game",
      "Game": "Crash Bandicoot 4: It's About Time",
      "Studio": "Toys for Bob \/ Activision",
      "Winner": 0
     },
     {
      "Year": 2020,
      "Category": "Best Family Game",
      "Game": "Fall Guys",
      "Studio": "Mediatonic \/ Devolver Digital",
      "Winner": 0
     },
     {
      "Year": 2020,
      "Category": "Best Family Game",
      "Game": "Mario Kart Live: Home Circuit",
      "Studio": "Velan Studios \/ Nintendo",
      "Winner": 0
     },
     {
      "Year": 2020,
      "Category": "Best Family Game",
      "Game": "Minecraft Dungeons",
      "Studio": "Mojang Studios \/ Xbox Game Studios",
      "Winner": 0
     },
     {
      "Year": 2020,
      "Category": "Best Family Game",
      "Game": "Paper Mario: The Origami King",
      "Studio": "Intelligent Systems\/Nintendo",
      "Winner": 0
     },
     {
      "Year": 2020,
      "Category": "Best Sim\/Strategy Game",
      "Game": "Microsoft Flight Simulator",
      "Studio": "Asobo Studio\/Xbox Game Studios",
      "Winner": 1
     },
     {
      "Year": 2020,
      "Category": "Best Sim\/Strategy Game",
      "Game": "Crusader Kings III",
      "Studio": "Paradox Interactive",
      "Winner": 0
     },
     {
      "Year": 2020,
      "Category": "Best Sim\/Strategy Game",
      "Game": "Desperados III",
      "Studio": "Mimimi Games \/ THQ Nordic",
      "Winner": 0
     },
     {
      "Year": 2020,
      "Category": "Best Sim\/Strategy Game",
      "Game": "Gears Tactics",
      "Studio": "Splash Damage \/ The Coalition \/ Xbox Game Studios",
      "Winner": 0
     },
     {
      "Year": 2020,
      "Category": "Best Sim\/Strategy Game",
      "Game": "XCOM: Chimera Squad",
      "Studio": "Firaxis Games \/ 2K Games",
      "Winner": 0
     },
     {
      "Year": 2020,
      "Category": "Best Sports\/Racing",
      "Game": "Tony Hawk's Pro Skater 1 + 2",
      "Studio": "Vicarious Visions \/ Activision",
      "Winner": 1
     },
     {
      "Year": 2020,
      "Category": "Best Sports\/Racing",
      "Game": "Dirt 5",
      "Studio": "Codemasters",
      "Winner": 0
     },
     {
      "Year": 2020,
      "Category": "Best Sports\/Racing",
      "Game": "F1 2020",
      "Studio": "Codemasters",
      "Winner": 0
     },
     {
      "Year": 2020,
      "Category": "Best Sports\/Racing",
      "Game": "FIFA 21",
      "Studio": "EA Vancouver\/EA Sports",
      "Winner": 0
     },
     {
      "Year": 2020,
      "Category": "Best Sports\/Racing",
      "Game": "NBA 2K21",
      "Studio": "Visual Concepts\/2K Sports",
      "Winner": 0
     },
     {
      "Year": 2020,
      "Category": "Best Multiplayer Present by Discord",
      "Game": "Among Us",
      "Studio": "Innersloth",
      "Winner": 1
     },
     {
      "Year": 2020,
      "Category": "Best Multiplayer Present by Discord",
      "Game": "Animal Crossing: New Horizons",
      "Studio": "Nintendo",
      "Winner": 0
     },
     {
      "Year": 2020,
      "Category": "Best Multiplayer Present by Discord",
      "Game": "Call of Duty: Warzone",
      "Studio": "Infinity Ward \/ Raven Software \/ Activision",
      "Winner": 0
     },
     {
      "Year": 2020,
      "Category": "Best Multiplayer Present by Discord",
      "Game": "Fall Guys",
      "Studio": "Mediatonic \/ Devolver Digital",
      "Winner": 0
     },
     {
      "Year": 2020,
      "Category": "Best Multiplayer Present by Discord",
      "Game": "Valorant",
      "Studio": "Riot Games",
      "Winner": 0
     },
     {
      "Year": 2020,
      "Category": "Best Debut Indie Game",
      "Game": "Phasmophobia",
      "Studio": "Kinetic Games",
      "Winner": 1
     },
     {
      "Year": 2020,
      "Category": "Best Debut Indie Game",
      "Game": "Carrion",
      "Studio": "Phobia Game Studio \/ Devolver Digital",
      "Winner": 0
     },
     {
      "Year": 2020,
      "Category": "Best Debut Indie Game",
      "Game": "Mortal Shell",
      "Studio": "Cold Symmetry \/ Playstack",
      "Winner": 0
     },
     {
      "Year": 2020,
      "Category": "Best Debut Indie Game",
      "Game": "Raji: An Ancient Epic",
      "Studio": "Nodding Heads Games \/ Super.com",
      "Winner": 0
     },
     {
      "Year": 2020,
      "Category": "Best Debut Indie Game",
      "Game": "Röki",
      "Studio": "Polygon Treehouse \/ United Label",
      "Winner": 0
     },
     {
      "Year": 2020,
      "Category": "Most Anticipated Game",
      "Game": "Elden Ring",
      "Studio": "FromSoftware\/Bandai Namco",
      "Winner": 1
     },
     {
      "Year": 2020,
      "Category": "Most Anticipated Game",
      "Game": "God of War sequel",
      "Studio": "Santa Monica Studio \/ Sony Interactive Entertainment",
      "Winner": 0
     },
     {
      "Year": 2020,
      "Category": "Most Anticipated Game",
      "Game": "Halo Infinite",
      "Studio": "343 Industries \/ Xbox Game Studios",
      "Winner": 0
     },
     {
      "Year": 2020,
      "Category": "Most Anticipated Game",
      "Game": "Horizon Forbidden West",
      "Studio": "Guerrilla Games\/SIE",
      "Winner": 0
     },
     {
      "Year": 2020,
      "Category": "Most Anticipated Game",
      "Game": "The Legend of Zelda: Breath of the Wild sequel",
      "Studio": "Nintendo",
      "Winner": 0
     },
     {
      "Year": 2020,
      "Category": "Most Anticipated Game",
      "Game": "Resident Evil Village",
      "Studio": "Capcom",
      "Winner": 0
     },
     {
      "Year": 2020,
      "Category": "Best eSports Game",
      "Game": "League of Legends",
      "Studio": "Riot Games",
      "Winner": 1
     },
     {
      "Year": 2020,
      "Category": "Best eSports Game",
      "Game": "Call of Duty: Modern Warfare",
      "Studio": "Infinity Ward \/ Raven Software \/ Activision",
      "Winner": 0
     },
     {
      "Year": 2020,
      "Category": "Best eSports Game",
      "Game": "Counter-Strike: Global Offensive",
      "Studio": "Valve",
      "Winner": 0
     },
     {
      "Year": 2020,
      "Category": "Best eSports Game",
      "Game": "Fortnite",
      "Studio": "Epic Games",
      "Winner": 0
     },
     {
      "Year": 2020,
      "Category": "Best eSports Game",
      "Game": "Valorant",
      "Studio": "Riot Games",
      "Winner": 0
     }
    ]
    }